{"FF": {"0a": {"0a": 0.753, "1a": 0.06, "2a": 0.0, "3a": 0.067, "4a": 0.004, "5a": 0.0, "6a": 0.0, "7a": 0.0, "8a": 0.0, "9a": 0.003, "9b": 0.0, "10a": 0.059, "10b": 0.001, "11b": 0.0, "12a": 0.053, "12b": 0.0, "13a": 0.0, "13b": 0.0, "14b": 0.0, "15a": 0.0, "15b": 0.0, "16b": 0.0}, "1a": {"0a": 0.064, "1a": 0.757, "2a": 0.05, "3a": 0.005, "4a": 0.056, "5a": 0.005, "6a": 0.0, "7a": 0.0, "8a": 0.0, "9a": 0.0, "9b": 0.0, "10a": 0.062, "10b": 0.001, "11b": 0.0, "12a": 0.0, "12b": 0.0, "13a": 0.0, "13b": 0.0, "14b": 0.0, "15a": 0.0, "15b": 0.0, "16b": 0.0}, "2a": {"0a": 0.0, "1a": 0.065, "2a": 0.739, "3a": 0.0, "4a": 0.006, "5a": 0.063, "6a": 0.0, "7a": 0.0, "8a": 0.0, "9a": 0.0, "9b": 0.0, "10a": 0.064, "10b": 0.001, "11b": 0.005, "12a": 0.0, "12b": 0.0, "13a": 0.057, "13b": 0.0, "14b": 0.0, "15a": 0.0, "15b": 0.0, "16b": 0.0}, "3a": {"0a": 0.058, "1a": 0.004, "2a": 0.0, "3a": 0.771, "4a": 0.06, "5a": 0.0, "6a": 0.048, "7a": 0.003, "8a": 0.0, "9a": 0.0, "9b": 0.0, "10a": 0.0, "10b": 0.0, "11b": 0.0, "12a": 0.056, "12b": 0.0, "13a": 0.0, "13b": 0.0, "14b": 0.0, "15a": 0.0, "15b": 0.0, "16b": 0.0}, "4a": {"0a": 0.003, "1a": 0.083, "2a": 0.003, "3a": 0.043, "4a": 0.752, "5a": 0.052, "6a": 0.007, "7a": 0.053, "8a": 0.004, "9a": 0.0, "9b": 0.0, "10a": 0.0, "10b": 0.0, "11b": 0.0, "12a": 0.0, "12b": 0.0, "13a": 0.0, "13b": 0.0, "14b": 0.0, "15a": 0.0, "15b": 0.0, "16b": 0.0}, "5a": {"0a": 0.0, "1a": 0.005, "2a": 0.057, "3a": 0.0, "4a": 0.056, "5a": 0.759, "6a": 0.0, "7a": 0.003, "8a": 0.061, "9a": 0.0, "9b": 0.0, "10a": 0.0, "10b": 0.0, "11b": 0.0, "12a": 0.0, "12b": 0.0, "13a": 0.059, "13b": 0.0, "14b": 0.0, "15a": 0.0, "15b": 0.0, "16b": 0.0}, "6a": {"0a": 0.0, "1a": 0.0, "2a": 0.0, "3a": 0.053, "4a": 0.005, "5a": 0.0, "6a": 0.765, "7a": 0.058, "8a": 0.0, "9a": 0.0, "9b": 0.0, "10a": 0.0, "10b": 0.0, "11b": 0.0, "12a": 0.054, "12b": 0.0, "13a": 0.0, "13b": 0.0, "14b": 0.008, "15a": 0.043, "15b": 0.014, "16b": 0.0}, "7a": {"0a": 0.0, "1a": 0.0, "2a": 0.0, "3a": 0.002, "4a": 0.056, "5a": 0.003, "6a": 0.051, "7a": 0.764, "8a": 0.053, "9a": 0.0, "9b": 0.0, "10a": 0.0, "10b": 0.0, "11b": 0.0, "12a": 0.0, "12b": 0.0, "13a": 0.0, "13b": 0.0, "14b": 0.0, "15a": 0.058, "15b": 0.013, "16b": 0.0}, "8a": {"0a": 0.0, "1a": 0.0, "2a": 0.0, "3a": 0.0, "4a": 0.009, "5a": 0.064, "6a": 0.0, "7a": 0.042, "8a": 0.754, "9a": 0.0, "9b": 0.0, "10a": 0.0, "10b": 0.0, "11b": 0.0, "12a": 0.0, "12b": 0.0, "13a": 0.064, "13b": 0.0, "14b": 0.0, "15a": 0.053, "15b": 0.011, "16b": 0.003}, "9a": {"0a": 0.042, "1a": 0.0, "2a": 0.0, "3a": 0.0, "4a": 0.0, "5a": 0.0, "6a": 0.0, "7a": 0.0, "8a": 0.0, "9a": 0.363, "9b": 0.275, "10a": 0.098, "10b": 0.022, "11b": 0.0, "12a": 0.2, "12b": 0.0, "13a": 0.0, "13b": 0.0, "14b": 0.0, "15a": 0.0, "15b": 0.0, "16b": 0.0}, "9b": {"0a": 0, "1a": 0, "2a": 0, "3a": 0, "4a": 0, "5a": 0, "6a": 0, "7a": 0, "8a": 0, "9a": 0, "9b": 1, "10a": 0, "10b": 0, "11b": 0, "12a": 0, "12b": 0, "13a": 0, "13b": 0, "14b": 0, "15a": 0, "15b": 0, "16b": 0}, "10a": {"0a": 0.011, "1a": 0.173, "2a": 0.012, "3a": 0.0, "4a": 0.0, "5a": 0.0, "6a": 0.0, "7a": 0.0, "8a": 0.0, "9a": 0.0, "9b": 0.0, "10a": 0.625, "10b": 0.179, "11b": 0.0, "12a": 0.0, "12b": 0.0, "13a": 0.0, "13b": 0.0, "14b": 0.0, "15a": 0.0, "15b": 0.0, "16b": 0.0}, "10b": {"0a": 0.0, "1a": 0.007, "2a": 0.0, "3a": 0.0, "4a": 0.0, "5a": 0.0, "6a": 0.0, "7a": 0.0, "8a": 0.0, "9a": 0.0, "9b": 0.0, "10a": 0.266, "10b": 0.727, "11b": 0.0, "12a": 0.0, "12b": 0.0, "13a": 0.0, "13b": 0.0, "14b": 0.0, "15a": 0.0, "15b": 0.0, "16b": 0.0}, "11b": {"0a": 0.0, "1a": 0.0, "2a": 0.003, "3a": 0.0, "4a": 0.0, "5a": 0.0, "6a": 0.0, "7a": 0.0, "8a": 0.0, "9a": 0.0, "9b": 0.0, "10a": 0.026, "10b": 0.036, "11b": 0.879, "12a": 0.0, "12b": 0.0, "13a": 0.056, "13b": 0.0, "14b": 0.0, "15a": 0.0, "15b": 0.0, "16b": 0.0}, "12a": {"0a": 0.001, "1a": 0.0, "2a": 0.0, "3a": 0.032, "4a": 0.0, "5a": 0.0, "6a": 0.004, "7a": 0.0, "8a": 0.0, "9a": 0.0, "9b": 0.0, "10a": 0.0, "10b": 0.0, "11b": 0.0, "12a": 0.93, "12b": 0.033, "13a": 0.0, "13b": 0.0, "14b": 0.0, "15a": 0.0, "15b": 0.0, "16b": 0.0}, "12b": {"0a": 0.0, "1a": 0.0, "2a": 0.0, "3a": 0.0, "4a": 0.0, "5a": 0.0, "6a": 0.0, "7a": 0.0, "8a": 0.0, "9a": 0.0, "9b": 0.0, "10a": 0.0, "10b": 0.0, "11b": 0.0, "12a": 0.633, "12b": 0.367, "13a": 0.0, "13b": 0.0, "14b": 0.0, "15a": 0.0, "15b": 0.0, "16b": 0.0}, "13a": {"0a": 0.0, "1a": 0.0, "2a": 0.006, "3a": 0.0, "4a": 0.0, "5a": 0.048, "6a": 0.0, "7a": 0.0, "8a": 0.003, "9a": 0.0, "9b": 0.0, "10a": 0.0, "10b": 0.0, "11b": 0.0, "12a": 0.0, "12b": 0.0, "13a": 0.885, "13b": 0.058, "14b": 0.0, "15a": 0.0, "15b": 0.0, "16b": 0.0}, "13b": {"0a": 0.0, "1a": 0.0, "2a": 0.0, "3a": 0.0, "4a": 0.0, "5a": 0.0, "6a": 0.0, "7a": 0.0, "8a": 0.0, "9a": 0.0, "9b": 0.0, "10a": 0.0, "10b": 0.0, "11b": 0.0, "12a": 0.0, "12b": 0.0, "13a": 0.527, "13b": 0.473, "14b": 0.0, "15a": 0.0, "15b": 0.0, "16b": 0.0}, "14b": {"0a": 0.0, "1a": 0.0, "2a": 0.0, "3a": 0.0, "4a": 0.0, "5a": 0.0, "6a": 0.002, "7a": 0.0, "8a": 0.0, "9a": 0.0, "9b": 0.0, "10a": 0.0, "10b": 0.0, "11b": 0.0, "12a": 0.052, "12b": 0.001, "13a": 0.0, "13b": 0.0, "14b": 0.878, "15a": 0.014, "15b": 0.053, "16b": 0.0}, "15a": {"0a": 0.0, "1a": 0.0, "2a": 0.0, "3a": 0.0, "4a": 0.001, "5a": 0.0, "6a": 0.017, "7a": 0.309, "8a": 0.021, "9a": 0.0, "9b": 0.0, "10a": 0.0, "10b": 0.0, "11b": 0.0, "12a": 0.0, "12b": 0.0, "13a": 0.0, "13b": 0.0, "14b": 0.0, "15a": 0.271, "15b": 0.381, "16b": 0.0}, "15b": {"0a": 0.0, "1a": 0.0, "2a": 0.0, "3a": 0.0, "4a": 0.0, "5a": 0.0, "6a": 0.0, "7a": 0.029, "8a": 0.001, "9a": 0.0, "9b": 0.0, "10a": 0.0, "10b": 0.0, "11b": 0.0, "12a": 0.0, "12b": 0.0, "13a": 0.0, "13b": 0.0, "14b": 0.0, "15a": 0.106, "15b": 0.864, "16b": 0.0}, "16b": {"0a": 0.0, "1a": 0.0, "2a": 0.0, "3a": 0.0, "4a": 0.0, "5a": 0.0, "6a": 0.0, "7a": 0.0, "8a": 0.001, "9a": 0.0, "9b": 0.0, "10a": 0.0, "10b": 0.0, "11b": 0.0, "12a": 0.0, "12b": 0.0, "13a": 0.064, "13b": 0.004, "14b": 0.0, "15a": 0.012, "15b": 0.052, "16b": 0.867}}, "SL": {"0a": {"0a": 0.488, "1a": 0.075, "2a": 0.001, "3a": 0.146, "4a": 0.016, "5a": 0.0, "6a": 0.004, "7a": 0.0, "8a": 0.0, "9b": 0.018, "10a": 0.055, "10b": 0.097, "11b": 0.0, "12a": 0.056, "12b": 0.044, "13a": 0.0, "13b": 0.0, "14a": 0.0, "14b": 0.0, "15a": 0.0, "15b": 0.0, "16a": 0.0, "16b": 0.0}, "1a": {"0a": 0.078, "1a": 0.506, "2a": 0.07, "3a": 0.022, "4a": 0.142, "5a": 0.023, "6a": 0.0, "7a": 0.002, "8a": 0.0, "9b": 0.0, "10a": 0.066, "10b": 0.091, "11b": 0.0, "12a": 0.0, "12b": 0.0, "13a": 0.0, "13b": 0.0, "14a": 0.0, "14b": 0.0, "15a": 0.0, "15b": 0.0, "16a": 0.0, "16b": 0.0}, "2a": {"0a": 0.0, "1a": 0.065, "2a": 0.494, "3a": 0.0, "4a": 0.03, "5a": 0.129, "6a": 0.0, "7a": 0.0, "8a": 0.002, "9b": 0.0, "10a": 0.068, "10b": 0.095, "11b": 0.019, "12a": 0.0, "12b": 0.0, "13a": 0.045, "13b": 0.053, "14a": 0.0, "14b": 0.0, "15a": 0.0, "15b": 0.0, "16a": 0.0, "16b": 0.0}, "3a": {"0a": 0.138, "1a": 0.008, "2a": 0.0, "3a": 0.495, "4a": 0.063, "5a": 0.0, "6a": 0.15, "7a": 0.028, "8a": 0.0, "9b": 0.0, "10a": 0.001, "10b": 0.002, "11b": 0.0, "12a": 0.105, "12b": 0.007, "13a": 0.0, "13b": 0.0, "14a": 0.0, "14b": 0.0, "15a": 0.003, "15b": 0.0, "16a": 0.0, "16b": 0.0}, "4a": {"0a": 0.016, "1a": 0.135, "2a": 0.019, "3a": 0.084, "4a": 0.488, "5a": 0.075, "6a": 0.023, "7a": 0.138, "8a": 0.018, "9b": 0.0, "10a": 0.002, "10b": 0.0, "11b": 0.0, "12a": 0.0, "12b": 0.0, "13a": 0.0, "13b": 0.0, "14a": 0.0, "14b": 0.0, "15a": 0.002, "15b": 0.0, "16a": 0.0, "16b": 0.0}, "5a": {"0a": 0.0, "1a": 0.015, "2a": 0.153, "3a": 0.0, "4a": 0.072, "5a": 0.485, "6a": 0.0, "7a": 0.021, "8a": 0.139, "9b": 0.0, "10a": 0.002, "10b": 0.0, "11b": 0.0, "12a": 0.0, "12b": 0.0, "13a": 0.104, "13b": 0.007, "14a": 0.0, "14b": 0.0, "15a": 0.002, "15b": 0.0, "16a": 0.0, "16b": 0.0}, "6a": {"0a": 0.001, "1a": 0.0, "2a": 0.0, "3a": 0.136, "4a": 0.016, "5a": 0.0, "6a": 0.503, "7a": 0.074, "8a": 0.0, "9b": 0.0, "10a": 0.0, "10b": 0.0, "11b": 0.0, "12a": 0.087, "12b": 0.0, "13a": 0.0, "13b": 0.0, "14a": 0.017, "14b": 0.0, "15a": 0.166, "15b": 0.0, "16a": 0.0, "16b": 0.0}, "7a": {"0a": 0.0, "1a": 0.003, "2a": 0.001, "3a": 0.019, "4a": 0.119, "5a": 0.019, "6a": 0.075, "7a": 0.503, "8a": 0.084, "9b": 0.0, "10a": 0.0, "10b": 0.0, "11b": 0.0, "12a": 0.0, "12b": 0.0, "13a": 0.0, "13b": 0.0, "14a": 0.0, "14b": 0.0, "15a": 0.177, "15b": 0.0, "16a": 0.0, "16b": 0.0}, "8a": {"0a": 0.0, "1a": 0.0, "2a": 0.002, "3a": 0.0, "4a": 0.018, "5a": 0.126, "6a": 0.0, "7a": 0.071, "8a": 0.498, "9b": 0.0, "10a": 0.0, "10b": 0.0, "11b": 0.0, "12a": 0.0, "12b": 0.0, "13a": 0.111, "13b": 0.0, "14a": 0.0, "14b": 0.0, "15a": 0.15, "15b": 0.0, "16a": 0.024, "16b": 0.0}, "9b": {"0a": 0.02, "1a": 0.0, "2a": 0.0, "3a": 0.0, "4a": 0.0, "5a": 0.0, "6a": 0.0, "7a": 0.0, "8a": 0.0, "9b": 0.723, "10a": 0.015, "10b": 0.088, "11b": 0.0, "12a": 0.018, "12b": 0.136, "13a": 0.0, "13b": 0.0, "14a": 0.0, "14b": 0.0, "15a": 0.0, "15b": 0.0, "16a": 0.0, "16b": 0.0}, "10a": {"0a": 0.043, "1a": 0.32, "2a": 0.046, "3a": 0.002, "4a": 0.015, "5a": 0.003, "6a": 0.0, "7a": 0.0, "8a": 0.0, "9b": 0.0, "10a": 0.13, "10b": 0.441, "11b": 0.0, "12a": 0.0, "12b": 0.0, "13a": 0.0, "13b": 0.0, "14a": 0.0, "14b": 0.0, "15a": 0.0, "15b": 0.0, "16a": 0.0, "16b": 0.0}, "10b": {"0a": 0.011, "1a": 0.097, "2a": 0.022, "3a": 0.0, "4a": 0.001, "5a": 0.001, "6a": 0.0, "7a": 0.0, "8a": 0.0, "9b": 0.0, "10a": 0.062, "10b": 0.806, "11b": 0.0, "12a": 0.0, "12b": 0.0, "13a": 0.0, "13b": 0.0, "14a": 0.0, "14b": 0.0, "15a": 0.0, "15b": 0.0, "16a": 0.0, "16b": 0.0}, "11b": {"0a": 0.0, "1a": 0.0, "2a": 0.02, "3a": 0.0, "4a": 0.0, "5a": 0.0, "6a": 0.0, "7a": 0.0, "8a": 0.0, "9b": 0.0, "10a": 0.009, "10b": 0.082, "11b": 0.738, "12a": 0.0, "12b": 0.0, "13a": 0.013, "13b": 0.138, "14a": 0.0, "14b": 0.0, "15a": 0.0, "15b": 0.0, "16a": 0.0, "16b": 0.0}, "12a": {"0a": 0.005, "1a": 0.0, "2a": 0.0, "3a": 0.069, "4a": 0.0, "5a": 0.0, "6a": 0.036, "7a": 0.0, "8a": 0.0, "9b": 0.0, "10a": 0.0, "10b": 0.0, "11b": 0.0, "12a": 0.773, "12b": 0.101, "13a": 0.0, "13b": 0.0, "14a": 0.015, "14b": 0.0, "15a": 0.001, "15b": 0.0, "16a": 0.0, "16b": 0.0}, "12b": {"0a": 0, "1a": 0, "2a": 0, "3a": 0, "4a": 0, "5a": 0, "6a": 0, "7a": 0, "8a": 0, "9b": 0, "10a": 0, "10b": 0, "11b": 0, "12a": 0, "12b": 1, "13a": 0, "13b": 0, "14a": 0, "14b": 0, "15a": 0, "15b": 0, "16a": 0, "16b": 0}, "13a": {"0a": 0.0, "1a": 0.0, "2a": 0.005, "3a": 0.0, "4a": 0.0, "5a": 0.03, "6a": 0.0, "7a": 0.0, "8a": 0.023, "9b": 0.0, "10a": 0.0, "10b": 0.0, "11b": 0.0, "12a": 0.0, "12b": 0.0, "13a": 0.829, "13b": 0.094, "14a": 0.0, "14b": 0.0, "15a": 0.001, "15b": 0.0, "16a": 0.017, "16b": 0.001}, "13b": {"0a": 0, "1a": 0, "2a": 0, "3a": 0, "4a": 0, "5a": 0, "6a": 0, "7a": 0, "8a": 0, "9b": 0, "10a": 0, "10b": 0, "11b": 0, "12a": 0, "12b": 0, "13a": 0, "13b": 1, "14a": 0, "14b": 0, "15a": 0, "15b": 0, "16a": 0, "16b": 0}, "14a": {"0a": 0.0, "1a": 0.0, "2a": 0.0, "3a": 0.0, "4a": 0.0, "5a": 0.0, "6a": 0.005, "7a": 0.0, "8a": 0.0, "9b": 0.0, "10a": 0.0, "10b": 0.0, "11b": 0.0, "12a": 0.057, "12b": 0.023, "13a": 0.0, "13b": 0.0, "14a": 0.75, "14b": 0.118, "15a": 0.041, "15b": 0.006, "16a": 0.0, "16b": 0.0}, "14b": {"0a": 0, "1a": 0, "2a": 0, "3a": 0, "4a": 0, "5a": 0, "6a": 0, "7a": 0, "8a": 0, "9b": 0, "10a": 0, "10b": 0, "11b": 0, "12a": 0, "12b": 0, "13a": 0, "13b": 0, "14a": 0, "14b": 1, "15a": 0, "15b": 0, "16a": 0, "16b": 0}, "15a": {"0a": 0.0, "1a": 0.0, "2a": 0.0, "3a": 0.0, "4a": 0.001, "5a": 0.002, "6a": 0.011, "7a": 0.076, "8a": 0.012, "9b": 0.0, "10a": 0.0, "10b": 0.0, "11b": 0.0, "12a": 0.0, "12b": 0.0, "13a": 0.0, "13b": 0.0, "14a": 0.0, "14b": 0.0, "15a": 0.802, "15b": 0.095, "16a": 0.001, "16b": 0.0}, "15b": {"0a": 0.0, "1a": 0.0, "2a": 0.0, "3a": 0.0, "4a": 0.0, "5a": 0.0, "6a": 0.0, "7a": 0.009, "8a": 0.0, "9b": 0.0, "10a": 0.0, "10b": 0.0, "11b": 0.0, "12a": 0.0, "12b": 0.0, "13a": 0.0, "13b": 0.0, "14a": 0.0, "14b": 0.0, "15a": 0.617, "15b": 0.374, "16a": 0.0, "16b": 0.0}, "16a": {"0a": 0.0, "1a": 0.0, "2a": 0.0, "3a": 0.0, "4a": 0.0, "5a": 0.0, "6a": 0.0, "7a": 0.0, "8a": 0.007, "9b": 0.0, "10a": 0.0, "10b": 0.0, "11b": 0.0, "12a": 0.0, "12b": 0.0, "13a": 0.062, "13b": 0.002, "14a": 0.0, "14b": 0.0, "15a": 0.062, "15b": 0.01, "16a": 0.717, "16b": 0.14}, "16b": {"0a": 0, "1a": 0, "2a": 0, "3a": 0, "4a": 0, "5a": 0, "6a": 0, "7a": 0, "8a": 0, "9b": 0, "10a": 0, "10b": 0, "11b": 0, "12a": 0, "12b": 0, "13a": 0, "13b": 0, "14a": 0, "14b": 0, "15a": 0, "15b": 0, "16a": 0, "16b": 1}}, "FT": {"0a": {"0a": 0.609, "1a": 0.115, "2a": 0.0, "3a": 0.074, "4a": 0.013, "5a": 0.0, "6a": 0.0, "7a": 0.0, "8a": 0.0, "9a": 0.008, "9b": 0.0, "10a": 0.05, "10b": 0.019, "11b": 0.0, "12a": 0.112, "12b": 0.0, "13a": 0.0, "13b": 0.0, "14a": 0.0, "14b": 0.0, "15a": 0.0, "15b": 0.0, "16b": 0.0}, "1a": {"0a": 0.082, "1a": 0.634, "2a": 0.106, "3a": 0.01, "4a": 0.075, "5a": 0.01, "6a": 0.0, "7a": 0.0, "8a": 0.0, "9a": 0.0, "9b": 0.0, "10a": 0.047, "10b": 0.035, "11b": 0.0, "12a": 0.001, "12b": 0.0, "13a": 0.0, "13b": 0.0, "14a": 0.0, "14b": 0.0, "15a": 0.0, "15b": 0.0, "16b": 0.0}, "2a": {"0a": 0.0, "1a": 0.114, "2a": 0.641, "3a": 0.0, "4a": 0.008, "5a": 0.064, "6a": 0.0, "7a": 0.0, "8a": 0.0, "9a": 0.0, "9b": 0.0, "10a": 0.038, "10b": 0.025, "11b": 0.007, "12a": 0.0, "12b": 0.0, "13a": 0.102, "13b": 0.001, "14a": 0.0, "14b": 0.0, "15a": 0.0, "15b": 0.0, "16b": 0.0}, "3a": {"0a": 0.061, "1a": 0.011, "2a": 0.0, "3a": 0.644, "4a": 0.099, "5a": 0.0, "6a": 0.074, "7a": 0.009, "8a": 0.0, "9a": 0.0, "9b": 0.0, "10a": 0.0, "10b": 0.0, "11b": 0.0, "12a": 0.102, "12b": 0.0, "13a": 0.0, "13b": 0.0, "14a": 0.0, "14b": 0.0, "15a": 0.0, "15b": 0.0, "16b": 0.0}, "4a": {"0a": 0.007, "1a": 0.069, "2a": 0.006, "3a": 0.107, "4a": 0.641, "5a": 0.096, "6a": 0.01, "7a": 0.059, "8a": 0.005, "9a": 0.0, "9b": 0.0, "10a": 0.0, "10b": 0.0, "11b": 0.0, "12a": 0.0, "12b": 0.0, "13a": 0.0, "13b": 0.0, "14a": 0.0, "14b": 0.0, "15a": 0.0, "15b": 0.0, "16b": 0.0}, "5a": {"0a": 0.001, "1a": 0.017, "2a": 0.05, "3a": 0.0, "4a": 0.106, "5a": 0.635, "6a": 0.0, "7a": 0.005, "8a": 0.069, "9a": 0.0, "9b": 0.0, "10a": 0.0, "10b": 0.0, "11b": 0.0, "12a": 0.0, "12b": 0.0, "13a": 0.112, "13b": 0.005, "14a": 0.0, "14b": 0.0, "15a": 0.0, "15b": 0.0, "16b": 0.0}, "6a": {"0a": 0.0, "1a": 0.0, "2a": 0.0, "3a": 0.054, "4a": 0.012, "5a": 0.0, "6a": 0.656, "7a": 0.071, "8a": 0.0, "9a": 0.0, "9b": 0.0, "10a": 0.0, "10b": 0.0, "11b": 0.0, "12a": 0.103, "12b": 0.0, "13a": 0.0, "13b": 0.0, "14a": 0.01, "14b": 0.0, "15a": 0.094, "15b": 0.0, "16b": 0.0}, "7a": {"0a": 0.0, "1a": 0.0, "2a": 0.0, "3a": 0.015, "4a": 0.07, "5a": 0.013, "6a": 0.109, "7a": 0.603, "8a": 0.099, "9a": 0.0, "9b": 0.0, "10a": 0.0, "10b": 0.0, "11b": 0.0, "12a": 0.0, "12b": 0.0, "13a": 0.001, "13b": 0.0, "14a": 0.0, "14b": 0.0, "15a": 0.088, "15b": 0.002, "16b": 0.0}, "8a": {"0a": 0.0, "1a": 0.0, "2a": 0.0, "3a": 0.0, "4a": 0.012, "5a": 0.061, "6a": 0.0, "7a": 0.088, "8a": 0.635, "9a": 0.0, "9b": 0.0, "10a": 0.0, "10b": 0.0, "11b": 0.0, "12a": 0.0, "12b": 0.0, "13a": 0.103, "13b": 0.006, "14a": 0.0, "14b": 0.0, "15a": 0.08, "15b": 0.0, "16b": 0.015}, "9a": {"0a": 0.042, "1a": 0.0, "2a": 0.0, "3a": 0.0, "4a": 0.0, "5a": 0.0, "6a": 0.0, "7a": 0.0, "8a": 0.0, "9a": 0.334, "9b": 0.295, "10a": 0.016, "10b": 0.097, "11b": 0.0, "12a": 0.204, "12b": 0.012, "13a": 0.0, "13b": 0.0, "14a": 0.0, "14b": 0.0, "15a": 0.0, "15b": 0.0, "16b": 0.0}, "9b": {"0a": 0, "1a": 0, "2a": 0, "3a": 0, "4a": 0, "5a": 0, "6a": 0, "7a": 0, "8a": 0, "9a": 0, "9b": 1, "10a": 0, "10b": 0, "11b": 0, "12a": 0, "12b": 0, "13a": 0, "13b": 0, "14a": 0, "14b": 0, "15a": 0, "15b": 0, "16b": 0}, "10a": {"0a": 0.04, "1a": 0.34, "2a": 0.046, "3a": 0.0, "4a": 0.001, "5a": 0.0, "6a": 0.0, "7a": 0.0, "8a": 0.0, "9a": 0.0, "9b": 0.0, "10a": 0.202, "10b": 0.371, "11b": 0.0, "12a": 0.0, "12b": 0.0, "13a": 0.0, "13b": 0.0, "14a": 0.0, "14b": 0.0, "15a": 0.0, "15b": 0.0, "16b": 0.0}, "10b": {"0a": 0.006, "1a": 0.033, "2a": 0.006, "3a": 0.0, "4a": 0.0, "5a": 0.0, "6a": 0.0, "7a": 0.0, "8a": 0.0, "9a": 0.0, "9b": 0.001, "10a": 0.072, "10b": 0.882, "11b": 0.0, "12a": 0.0, "12b": 0.0, "13a": 0.0, "13b": 0.0, "14a": 0.0, "14b": 0.0, "15a": 0.0, "15b": 0.0, "16b": 0.0}, "11b": {"0a": 0.0, "1a": 0.0, "2a": 0.015, "3a": 0.0, "4a": 0.0, "5a": 0.0, "6a": 0.0, "7a": 0.0, "8a": 0.0, "9a": 0.0, "9b": 0.0, "10a": 0.013, "10b": 0.105, "11b": 0.804, "12a": 0.0, "12b": 0.0, "13a": 0.037, "13b": 0.026, "14a": 0.0, "14b": 0.0, "15a": 0.0, "15b": 0.0, "16b": 0.0}, "12a": {"0a": 0.008, "1a": 0.0, "2a": 0.0, "3a": 0.065, "4a": 0.0, "5a": 0.0, "6a": 0.007, "7a": 0.0, "8a": 0.0, "9a": 0.0, "9b": 0.0, "10a": 0.0, "10b": 0.0, "11b": 0.0, "12a": 0.838, "12b": 0.082, "13a": 0.0, "13b": 0.0, "14a": 0.0, "14b": 0.0, "15a": 0.0, "15b": 0.0, "16b": 0.0}, "12b": {"0a": 0.0, "1a": 0.0, "2a": 0.0, "3a": 0.004, "4a": 0.0, "5a": 0.0, "6a": 0.0, "7a": 0.0, "8a": 0.0, "9a": 0.0, "9b": 0.0, "10a": 0.0, "10b": 0.0, "11b": 0.0, "12a": 0.606, "12b": 0.39, "13a": 0.0, "13b": 0.0, "14a": 0.0, "14b": 0.0, "15a": 0.0, "15b": 0.0, "16b": 0.0}, "13a": {"0a": 0.0, "1a": 0.0, "2a": 0.024, "3a": 0.0, "4a": 0.001, "5a": 0.173, "6a": 0.0, "7a": 0.0, "8a": 0.018, "9a": 0.0, "9b": 0.0, "10a": 0.0, "10b": 0.0, "11b": 0.0, "12a": 0.0, "12b": 0.0, "13a": 0.572, "13b": 0.212, "14a": 0.0, "14b": 0.0, "15a": 0.0, "15b": 0.0, "16b": 0.0}, "13b": {"0a": 0.0, "1a": 0.0, "2a": 0.001, "3a": 0.0, "4a": 0.0, "5a": 0.016, "6a": 0.0, "7a": 0.0, "8a": 0.004, "9a": 0.0, "9b": 0.0, "10a": 0.0, "10b": 0.0, "11b": 0.0, "12a": 0.0, "12b": 0.0, "13a": 0.347, "13b": 0.632, "14a": 0.0, "14b": 0.0, "15a": 0.0, "15b": 0.0, "16b": 0.0}, "14a": {"0a": 0.0, "1a": 0.0, "2a": 0.0, "3a": 0.001, "4a": 0.0, "5a": 0.0, "6a": 0.06, "7a": 0.0, "8a": 0.0, "9a": 0.0, "9b": 0.0, "10a": 0.0, "10b": 0.0, "11b": 0.0, "12a": 0.212, "12b": 0.003, "13a": 0.0, "13b": 0.0, "14a": 0.261, "14b": 0.32, "15a": 0.112, "15b": 0.031, "16b": 0.0}, "14b": {"0a": 0, "1a": 0, "2a": 0, "3a": 0, "4a": 0, "5a": 0, "6a": 0, "7a": 0, "8a": 0, "9a": 0, "9b": 0, "10a": 0, "10b": 0, "11b": 0, "12a": 0, "12b": 0, "13a": 0, "13b": 0, "14a": 0, "14b": 1, "15a": 0, "15b": 0, "16b": 0}, "15a": {"0a": 0.0, "1a": 0.0, "2a": 0.0, "3a": 0.0, "4a": 0.0, "5a": 0.0, "6a": 0.017, "7a": 0.16, "8a": 0.034, "9a": 0.0, "9b": 0.0, "10a": 0.0, "10b": 0.0, "11b": 0.0, "12a": 0.0, "12b": 0.0, "13a": 0.0, "13b": 0.0, "14a": 0.0, "14b": 0.0, "15a": 0.614, "15b": 0.175, "16b": 0.0}, "15b": {"0a": 0.0, "1a": 0.0, "2a": 0.0, "3a": 0.0, "4a": 0.0, "5a": 0.0, "6a": 0.003, "7a": 0.01, "8a": 0.002, "9a": 0.0, "9b": 0.0, "10a": 0.0, "10b": 0.0, "11b": 0.0, "12a": 0.0, "12b": 0.0, "13a": 0.0, "13b": 0.0, "14a": 0.0, "14b": 0.001, "15a": 0.279, "15b": 0.705, "16b": 0.0}, "16b": {"0a": 0.0, "1a": 0.0, "2a": 0.0, "3a": 0.0, "4a": 0.0, "5a": 0.0, "6a": 0.0, "7a": 0.0, "8a": 0.013, "9a": 0.0, "9b": 0.0, "10a": 0.0, "10b": 0.0, "11b": 0.0, "12a": 0.0, "12b": 0.0, "13a": 0.042, "13b": 0.035, "14a": 0.0, "14b": 0.0, "15a": 0.064, "15b": 0.055, "16b": 0.791}}, "CH": {"0a": {"0a": 0.785, "1a": 0.033, "2a": 0.0, "3a": 0.069, "4a": 0.001, "5a": 0.0, "6a": 0.0, "7a": 0.0, "8a": 0.0, "9b": 0.006, "10b": 0.076, "11b": 0.0, "12a": 0.021, "12b": 0.009, "13a": 0.0, "13b": 0.0, "14a": 0.0, "14b": 0.0, "15a": 0.0, "15b": 0.0, "16a": 0.0, "16b": 0.0}, "1a": {"0a": 0.029, "1a": 0.786, "2a": 0.03, "3a": 0.003, "4a": 0.067, "5a": 0.003, "6a": 0.0, "7a": 0.0, "8a": 0.0, "9b": 0.0, "10b": 0.082, "11b": 0.0, "12a": 0.0, "12b": 0.0, "13a": 0.0, "13b": 0.0, "14a": 0.0, "14b": 0.0, "15a": 0.0, "15b": 0.0, "16a": 0.0, "16b": 0.0}, "2a": {"0a": 0.0, "1a": 0.026, "2a": 0.783, "3a": 0.0, "4a": 0.002, "5a": 0.088, "6a": 0.0, "7a": 0.0, "8a": 0.0, "9b": 0.0, "10b": 0.059, "11b": 0.002, "12a": 0.0, "12b": 0.0, "13a": 0.035, "13b": 0.005, "14a": 0.0, "14b": 0.0, "15a": 0.0, "15b": 0.0, "16a": 0.0, "16b": 0.0}, "3a": {"0a": 0.096, "1a": 0.005, "2a": 0.0, "3a": 0.764, "4a": 0.024, "5a": 0.0, "6a": 0.08, "7a": 0.001, "8a": 0.0, "9b": 0.0, "10b": 0.0, "11b": 0.0, "12a": 0.03, "12b": 0.0, "13a": 0.0, "13b": 0.0, "14a": 0.0, "14b": 0.0, "15a": 0.0, "15b": 0.0, "16a": 0.0, "16b": 0.0}, "4a": {"0a": 0.001, "1a": 0.067, "2a": 0.001, "3a": 0.026, "4a": 0.78, "5a": 0.03, "6a": 0.004, "7a": 0.09, "8a": 0.001, "9b": 0.0, "10b": 0.0, "11b": 0.0, "12a": 0.0, "12b": 0.0, "13a": 0.0, "13b": 0.0, "14a": 0.0, "14b": 0.0, "15a": 0.0, "15b": 0.0, "16a": 0.0, "16b": 0.0}, "5a": {"0a": 0.0, "1a": 0.005, "2a": 0.064, "3a": 0.0, "4a": 0.027, "5a": 0.789, "6a": 0.0, "7a": 0.006, "8a": 0.081, "9b": 0.0, "10b": 0.0, "11b": 0.0, "12a": 0.0, "12b": 0.0, "13a": 0.028, "13b": 0.0, "14a": 0.0, "14b": 0.0, "15a": 0.0, "15b": 0.0, "16a": 0.0, "16b": 0.0}, "6a": {"0a": 0.0, "1a": 0.0, "2a": 0.0, "3a": 0.061, "4a": 0.001, "5a": 0.0, "6a": 0.806, "7a": 0.034, "8a": 0.0, "9b": 0.0, "10b": 0.0, "11b": 0.0, "12a": 0.024, "12b": 0.0, "13a": 0.0, "13b": 0.0, "14a": 0.004, "14b": 0.0, "15a": 0.07, "15b": 0.0, "16a": 0.0, "16b": 0.0}, "7a": {"0a": 0.0, "1a": 0.0, "2a": 0.0, "3a": 0.002, "4a": 0.075, "5a": 0.005, "6a": 0.029, "7a": 0.794, "8a": 0.026, "9b": 0.0, "10b": 0.0, "11b": 0.0, "12a": 0.0, "12b": 0.0, "13a": 0.0, "13b": 0.0, "14a": 0.0, "14b": 0.0, "15a": 0.069, "15b": 0.0, "16a": 0.0, "16b": 0.0}, "8a": {"0a": 0.0, "1a": 0.0, "2a": 0.0, "3a": 0.0, "4a": 0.0, "5a": 0.075, "6a": 0.0, "7a": 0.031, "8a": 0.79, "9b": 0.0, "10b": 0.0, "11b": 0.0, "12a": 0.0, "12b": 0.0, "13a": 0.021, "13b": 0.0, "14a": 0.0, "14b": 0.0, "15a": 0.082, "15b": 0.0, "16a": 0.001, "16b": 0.0}, "9b": {"0a": 0.002, "1a": 0.0, "2a": 0.0, "3a": 0.0, "4a": 0.0, "5a": 0.0, "6a": 0.0, "7a": 0.0, "8a": 0.0, "9b": 0.883, "10b": 0.031, "11b": 0.0, "12a": 0.019, "12b": 0.065, "13a": 0.0, "13b": 0.0, "14a": 0.0, "14b": 0.0, "15a": 0.0, "15b": 0.0, "16a": 0.0, "16b": 0.0}, "10b": {"0a": 0.001, "1a": 0.062, "2a": 0.005, "3a": 0.0, "4a": 0.0, "5a": 0.0, "6a": 0.0, "7a": 0.0, "8a": 0.0, "9b": 0.0, "10b": 0.932, "11b": 0.0, "12a": 0.0, "12b": 0.0, "13a": 0.0, "13b": 0.0, "14a": 0.0, "14b": 0.0, "15a": 0.0, "15b": 0.0, "16a": 0.0, "16b": 0.0}, "11b": {"0a": 0.0, "1a": 0.0, "2a": 0.001, "3a": 0.0, "4a": 0.0, "5a": 0.0, "6a": 0.0, "7a": 0.0, "8a": 0.0, "9b": 0.0, "10b": 0.026, "11b": 0.904, "12a": 0.0, "12b": 0.0, "13a": 0.016, "13b": 0.053, "14a": 0.0, "14b": 0.0, "15a": 0.0, "15b": 0.0, "16a": 0.0, "16b": 0.0}, "12a": {"0a": 0.0, "1a": 0.0, "2a": 0.0, "3a": 0.018, "4a": 0.0, "5a": 0.0, "6a": 0.006, "7a": 0.0, "8a": 0.0, "9b": 0.0, "10b": 0.0, "11b": 0.0, "12a": 0.943, "12b": 0.033, "13a": 0.0, "13b": 0.0, "14a": 0.0, "14b": 0.0, "15a": 0.0, "15b": 0.0, "16a": 0.0, "16b": 0.0}, "12b": {"0a": 0, "1a": 0, "2a": 0, "3a": 0, "4a": 0, "5a": 0, "6a": 0, "7a": 0, "8a": 0, "9b": 0, "10b": 0, "11b": 0, "12a": 0, "12b": 1, "13a": 0, "13b": 0, "14a": 0, "14b": 0, "15a": 0, "15b": 0, "16a": 0, "16b": 0}, "13a": {"0a": 0.0, "1a": 0.0, "2a": 0.001, "3a": 0.0, "4a": 0.0, "5a": 0.005, "6a": 0.0, "7a": 0.0, "8a": 0.002, "9b": 0.0, "10b": 0.0, "11b": 0.0, "12a": 0.0, "12b": 0.0, "13a": 0.976, "13b": 0.016, "14a": 0.0, "14b": 0.0, "15a": 0.0, "15b": 0.0, "16a": 0.0, "16b": 0.0}, "13b": {"0a": 0, "1a": 0, "2a": 0, "3a": 0, "4a": 0, "5a": 0, "6a": 0, "7a": 0, "8a": 0, "9b": 0, "10b": 0, "11b": 0, "12a": 0, "12b": 0, "13a": 0, "13b": 1, "14a": 0, "14b": 0, "15a": 0, "15b": 0, "16a": 0, "16b": 0}, "14a": {"0a": 0.0, "1a": 0.0, "2a": 0.0, "3a": 0.0, "4a": 0.0, "5a": 0.0, "6a": 0.0, "7a": 0.0, "8a": 0.0, "9b": 0.0, "10b": 0.0, "11b": 0.0, "12a": 0.063, "12b": 0.002, "13a": 0.0, "13b": 0.0, "14a": 0.809, "14b": 0.103, "15a": 0.022, "15b": 0.001, "16a": 0.0, "16b": 0.0}, "14b": {"0a": 0, "1a": 0, "2a": 0, "3a": 0, "4a": 0, "5a": 0, "6a": 0, "7a": 0, "8a": 0, "9b": 0, "10b": 0, "11b": 0, "12a": 0, "12b": 0, "13a": 0, "13b": 0, "14a": 0, "14b": 1, "15a": 0, "15b": 0, "16a": 0, "16b": 0}, "15a": {"0a": 0.0, "1a": 0.0, "2a": 0.0, "3a": 0.0, "4a": 0.0, "5a": 0.0, "6a": 0.005, "7a": 0.059, "8a": 0.002, "9b": 0.0, "10b": 0.0, "11b": 0.0, "12a": 0.0, "12b": 0.0, "13a": 0.0, "13b": 0.0, "14a": 0.0, "14b": 0.0, "15a": 0.861, "15b": 0.073, "16a": 0.0, "16b": 0.0}, "15b": {"0a": 0.0, "1a": 0.0, "2a": 0.0, "3a": 0.0, "4a": 0.0, "5a": 0.0, "6a": 0.001, "7a": 0.003, "8a": 0.0, "9b": 0.0, "10b": 0.0, "11b": 0.0, "12a": 0.0, "12b": 0.0, "13a": 0.0, "13b": 0.0, "14a": 0.0, "14b": 0.0, "15a": 0.502, "15b": 0.494, "16a": 0.0, "16b": 0.0}, "16a": {"0a": 0.0, "1a": 0.0, "2a": 0.0, "3a": 0.0, "4a": 0.0, "5a": 0.0, "6a": 0.0, "7a": 0.0, "8a": 0.003, "9b": 0.0, "10b": 0.0, "11b": 0.0, "12a": 0.0, "12b": 0.0, "13a": 0.05, "13b": 0.0, "14a": 0.0, "14b": 0.0, "15a": 0.018, "15b": 0.004, "16a": 0.861, "16b": 0.064}, "16b": {"0a": 0, "1a": 0, "2a": 0, "3a": 0, "4a": 0, "5a": 0, "6a": 0, "7a": 0, "8a": 0, "9b": 0, "10b": 0, "11b": 0, "12a": 0, "12b": 0, "13a": 0, "13b": 0, "14a": 0, "14b": 0, "15a": 0, "15b": 0, "16a": 0, "16b": 1}}, "CU": {"0a": {"0a": 0.441, "1a": 0.049, "2a": 0.0, "3a": 0.187, "4a": 0.014, "5a": 0.0, "6a": 0.011, "7a": 0.001, "8a": 0.0, "9b": 0.018, "10b": 0.206, "11b": 0.0, "12a": 0.03, "12b": 0.043, "13a": 0.0, "13b": 0.0, "14a": 0.0, "14b": 0.0, "15a": 0.0, "15b": 0.0, "16a": 0.0, "16b": 0.0}, "1a": {"0a": 0.046, "1a": 0.465, "2a": 0.054, "3a": 0.019, "4a": 0.155, "5a": 0.019, "6a": 0.003, "7a": 0.009, "8a": 0.001, "9b": 0.0, "10b": 0.229, "11b": 0.0, "12a": 0.0, "12b": 0.0, "13a": 0.0, "13b": 0.0, "14a": 0.0, "14b": 0.0, "15a": 0.0, "15b": 0.0, "16a": 0.0, "16b": 0.0}, "2a": {"0a": 0.0, "1a": 0.059, "2a": 0.427, "3a": 0.0, "4a": 0.025, "5a": 0.178, "6a": 0.0, "7a": 0.0, "8a": 0.01, "9b": 0.0, "10b": 0.199, "11b": 0.024, "12a": 0.0, "12b": 0.0, "13a": 0.035, "13b": 0.042, "14a": 0.0, "14b": 0.0, "15a": 0.001, "15b": 0.0, "16a": 0.0, "16b": 0.0}, "3a": {"0a": 0.169, "1a": 0.019, "2a": 0.0, "3a": 0.436, "4a": 0.053, "5a": 0.0, "6a": 0.168, "7a": 0.02, "8a": 0.0, "9b": 0.001, "10b": 0.011, "11b": 0.0, "12a": 0.087, "12b": 0.013, "13a": 0.0, "13b": 0.0, "14a": 0.002, "14b": 0.0, "15a": 0.021, "15b": 0.0, "16a": 0.0, "16b": 0.0}, "4a": {"0a": 0.023, "1a": 0.174, "2a": 0.028, "3a": 0.04, "4a": 0.445, "5a": 0.05, "6a": 0.011, "7a": 0.175, "8a": 0.027, "9b": 0.0, "10b": 0.016, "11b": 0.0, "12a": 0.0, "12b": 0.0, "13a": 0.0, "13b": 0.0, "14a": 0.0, "14b": 0.0, "15a": 0.011, "15b": 0.0, "16a": 0.0, "16b": 0.0}, "5a": {"0a": 0.0, "1a": 0.018, "2a": 0.177, "3a": 0.0, "4a": 0.045, "5a": 0.445, "6a": 0.0, "7a": 0.027, "8a": 0.167, "9b": 0.0, "10b": 0.016, "11b": 0.0, "12a": 0.0, "12b": 0.0, "13a": 0.083, "13b": 0.017, "14a": 0.0, "14b": 0.0, "15a": 0.004, "15b": 0.0, "16a": 0.001, "16b": 0.0}, "6a": {"0a": 0.007, "1a": 0.002, "2a": 0.0, "3a": 0.187, "4a": 0.028, "5a": 0.0, "6a": 0.446, "7a": 0.05, "8a": 0.001, "9b": 0.0, "10b": 0.0, "11b": 0.0, "12a": 0.072, "12b": 0.0, "13a": 0.0, "13b": 0.0, "14a": 0.013, "14b": 0.0, "15a": 0.194, "15b": 0.0, "16a": 0.0, "16b": 0.0}, "7a": {"0a": 0.0, "1a": 0.007, "2a": 0.003, "3a": 0.015, "4a": 0.167, "5a": 0.014, "6a": 0.051, "7a": 0.462, "8a": 0.055, "9b": 0.0, "10b": 0.001, "11b": 0.0, "12a": 0.0, "12b": 0.0, "13a": 0.0, "13b": 0.0, "14a": 0.0, "14b": 0.0, "15a": 0.225, "15b": 0.0, "16a": 0.0, "16b": 0.0}, "8a": {"0a": 0.0, "1a": 0.001, "2a": 0.014, "3a": 0.0, "4a": 0.022, "5a": 0.183, "6a": 0.0, "7a": 0.039, "8a": 0.433, "9b": 0.0, "10b": 0.0, "11b": 0.0, "12a": 0.0, "12b": 0.0, "13a": 0.069, "13b": 0.0, "14a": 0.0, "14b": 0.0, "15a": 0.217, "15b": 0.0, "16a": 0.022, "16b": 0.0}, "9b": {"0a": 0.018, "1a": 0.0, "2a": 0.0, "3a": 0.001, "4a": 0.0, "5a": 0.0, "6a": 0.0, "7a": 0.0, "8a": 0.0, "9b": 0.681, "10b": 0.083, "11b": 0.0, "12a": 0.021, "12b": 0.196, "13a": 0.0, "13b": 0.0, "14a": 0.0, "14b": 0.0, "15a": 0.0, "15b": 0.0, "16a": 0.0, "16b": 0.0}, "10b": {"0a": 0.027, "1a": 0.163, "2a": 0.015, "3a": 0.001, "4a": 0.014, "5a": 0.0, "6a": 0.0, "7a": 0.0, "8a": 0.0, "9b": 0.0, "10b": 0.78, "11b": 0.0, "12a": 0.0, "12b": 0.0, "13a": 0.0, "13b": 0.0, "14a": 0.0, "14b": 0.0, "15a": 0.0, "15b": 0.0, "16a": 0.0, "16b": 0.0}, "11b": {"0a": 0.0, "1a": 0.0, "2a": 0.031, "3a": 0.0, "4a": 0.0, "5a": 0.001, "6a": 0.0, "7a": 0.0, "8a": 0.0, "9b": 0.0, "10b": 0.082, "11b": 0.68, "12a": 0.0, "12b": 0.0, "13a": 0.027, "13b": 0.179, "14a": 0.0, "14b": 0.0, "15a": 0.0, "15b": 0.0, "16a": 0.0, "16b": 0.0}, "12a": {"0a": 0.011, "1a": 0.0, "2a": 0.0, "3a": 0.047, "4a": 0.0, "5a": 0.0, "6a": 0.046, "7a": 0.0, "8a": 0.0, "9b": 0.004, "10b": 0.0, "11b": 0.0, "12a": 0.719, "12b": 0.122, "13a": 0.0, "13b": 0.0, "14a": 0.032, "14b": 0.014, "15a": 0.005, "15b": 0.0, "16a": 0.0, "16b": 0.0}, "12b": {"0a": 0, "1a": 0, "2a": 0, "3a": 0, "4a": 0, "5a": 0, "6a": 0, "7a": 0, "8a": 0, "9b": 0, "10b": 0, "11b": 0, "12a": 0, "12b": 1, "13a": 0, "13b": 0, "14a": 0, "14b": 0, "15a": 0, "15b": 0, "16a": 0, "16b": 0}, "13a": {"0a": 0.0, "1a": 0.0, "2a": 0.003, "3a": 0.0, "4a": 0.0, "5a": 0.022, "6a": 0.0, "7a": 0.0, "8a": 0.012, "9b": 0.0, "10b": 0.0, "11b": 0.004, "12a": 0.0, "12b": 0.0, "13a": 0.802, "13b": 0.101, "14a": 0.0, "14b": 0.0, "15a": 0.004, "15b": 0.0, "16a": 0.035, "16b": 0.017}, "13b": {"0a": 0, "1a": 0, "2a": 0, "3a": 0, "4a": 0, "5a": 0, "6a": 0, "7a": 0, "8a": 0, "9b": 0, "10b": 0, "11b": 0, "12a": 0, "12b": 0, "13a": 0, "13b": 1, "14a": 0, "14b": 0, "15a": 0, "15b": 0, "16a": 0, "16b": 0}, "14a": {"0a": 0.0, "1a": 0.0, "2a": 0.0, "3a": 0.0, "4a": 0.0, "5a": 0.0, "6a": 0.021, "7a": 0.0, "8a": 0.0, "9b": 0.0, "10b": 0.0, "11b": 0.0, "12a": 0.111, "12b": 0.008, "13a": 0.0, "13b": 0.0, "14a": 0.516, "14b": 0.239, "15a": 0.1, "15b": 0.005, "16a": 0.0, "16b": 0.0}, "14b": {"0a": 0, "1a": 0, "2a": 0, "3a": 0, "4a": 0, "5a": 0, "6a": 0, "7a": 0, "8a": 0, "9b": 0, "10b": 0, "11b": 0, "12a": 0, "12b": 0, "13a": 0, "13b": 0, "14a": 0, "14b": 1, "15a": 0, "15b": 0, "16a": 0, "16b": 0}, "15a": {"0a": 0.0, "1a": 0.0, "2a": 0.0, "3a": 0.0, "4a": 0.003, "5a": 0.0, "6a": 0.013, "7a": 0.071, "8a": 0.005, "9b": 0.0, "10b": 0.0, "11b": 0.0, "12a": 0.0, "12b": 0.0, "13a": 0.0, "13b": 0.0, "14a": 0.001, "14b": 0.0, "15a": 0.82, "15b": 0.087, "16a": 0.0, "16b": 0.0}, "15b": {"0a": 0.0, "1a": 0.0, "2a": 0.0, "3a": 0.0, "4a": 0.0, "5a": 0.0, "6a": 0.004, "7a": 0.011, "8a": 0.001, "9b": 0.0, "10b": 0.0, "11b": 0.0, "12a": 0.0, "12b": 0.0, "13a": 0.0, "13b": 0.0, "14a": 0.0, "14b": 0.0, "15a": 0.739, "15b": 0.245, "16a": 0.0, "16b": 0.0}, "16a": {"0a": 0.0, "1a": 0.0, "2a": 0.0, "3a": 0.0, "4a": 0.0, "5a": 0.002, "6a": 0.0, "7a": 0.0, "8a": 0.019, "9b": 0.0, "10b": 0.0, "11b": 0.0, "12a": 0.0, "12b": 0.0, "13a": 0.151, "13b": 0.003, "14a": 0.0, "14b": 0.0, "15a": 0.105, "15b": 0.002, "16a": 0.481, "16b": 0.237}, "16b": {"0a": 0, "1a": 0, "2a": 0, "3a": 0, "4a": 0, "5a": 0, "6a": 0, "7a": 0, "8a": 0, "9b": 0, "10b": 0, "11b": 0, "12a": 0, "12b": 0, "13a": 0, "13b": 0, "14a": 0, "14b": 0, "15a": 0, "15b": 0, "16a": 0, "16b": 1}}, "FC": {"0a": {"0a": 0.583, "1a": 0.064, "2a": 0.0, "3a": 0.103, "4a": 0.014, "5a": 0.0, "6a": 0.001, "7a": 0.0, "8a": 0.0, "9b": 0.01, "10a": 0.059, "10b": 0.079, "11b": 0.0, "12a": 0.061, "12b": 0.026, "13a": 0.0, "13b": 0.0, "14a": 0.0, "14b": 0.0, "15a": 0.0, "15b": 0.0, "16a": 0.0, "16b": 0.0}, "1a": {"0a": 0.053, "1a": 0.591, "2a": 0.071, "3a": 0.009, "4a": 0.115, "5a": 0.019, "6a": 0.0, "7a": 0.002, "8a": 0.0, "9b": 0.0, "10a": 0.07, "10b": 0.07, "11b": 0.0, "12a": 0.0, "12b": 0.0, "13a": 0.0, "13b": 0.0, "14a": 0.0, "14b": 0.0, "15a": 0.0, "15b": 0.0, "16a": 0.0, "16b": 0.0}, "2a": {"0a": 0.0, "1a": 0.082, "2a": 0.552, "3a": 0.0, "4a": 0.019, "5a": 0.117, "6a": 0.0, "7a": 0.0, "8a": 0.001, "9b": 0.0, "10a": 0.074, "10b": 0.062, "11b": 0.014, "12a": 0.0, "12b": 0.0, "13a": 0.055, "13b": 0.024, "14a": 0.0, "14b": 0.0, "15a": 0.0, "15b": 0.0, "16a": 0.0, "16b": 0.0}, "3a": {"0a": 0.137, "1a": 0.017, "2a": 0.0, "3a": 0.568, "4a": 0.077, "5a": 0.0, "6a": 0.104, "7a": 0.017, "8a": 0.0, "9b": 0.0, "10a": 0.0, "10b": 0.0, "11b": 0.0, "12a": 0.079, "12b": 0.0, "13a": 0.0, "13b": 0.0, "14a": 0.0, "14b": 0.0, "15a": 0.001, "15b": 0.0, "16a": 0.0, "16b": 0.0}, "4a": {"0a": 0.01, "1a": 0.127, "2a": 0.011, "3a": 0.074, "4a": 0.567, "5a": 0.064, "6a": 0.013, "7a": 0.118, "8a": 0.011, "9b": 0.0, "10a": 0.001, "10b": 0.002, "11b": 0.0, "12a": 0.0, "12b": 0.0, "13a": 0.0, "13b": 0.0, "14a": 0.0, "14b": 0.0, "15a": 0.002, "15b": 0.0, "16a": 0.0, "16b": 0.0}, "5a": {"0a": 0.0, "1a": 0.013, "2a": 0.138, "3a": 0.0, "4a": 0.079, "5a": 0.573, "6a": 0.0, "7a": 0.02, "8a": 0.096, "9b": 0.0, "10a": 0.0, "10b": 0.0, "11b": 0.0, "12a": 0.0, "12b": 0.0, "13a": 0.079, "13b": 0.001, "14a": 0.0, "14b": 0.0, "15a": 0.001, "15b": 0.0, "16a": 0.0, "16b": 0.0}, "6a": {"0a": 0.001, "1a": 0.0, "2a": 0.0, "3a": 0.13, "4a": 0.014, "5a": 0.0, "6a": 0.575, "7a": 0.062, "8a": 0.0, "9b": 0.0, "10a": 0.0, "10b": 0.0, "11b": 0.0, "12a": 0.085, "12b": 0.0, "13a": 0.0, "13b": 0.0, "14a": 0.016, "14b": 0.0, "15a": 0.117, "15b": 0.0, "16a": 0.0, "16b": 0.0}, "7a": {"0a": 0.001, "1a": 0.001, "2a": 0.0, "3a": 0.015, "4a": 0.109, "5a": 0.012, "6a": 0.066, "7a": 0.584, "8a": 0.066, "9b": 0.0, "10a": 0.0, "10b": 0.0, "11b": 0.0, "12a": 0.0, "12b": 0.0, "13a": 0.0, "13b": 0.0, "14a": 0.0, "14b": 0.0, "15a": 0.146, "15b": 0.0, "16a": 0.0, "16b": 0.0}, "8a": {"0a": 0.0, "1a": 0.0, "2a": 0.0, "3a": 0.0, "4a": 0.014, "5a": 0.122, "6a": 0.0, "7a": 0.075, "8a": 0.576, "9b": 0.0, "10a": 0.0, "10b": 0.0, "11b": 0.0, "12a": 0.0, "12b": 0.0, "13a": 0.081, "13b": 0.0, "14a": 0.0, "14b": 0.0, "15a": 0.118, "15b": 0.0, "16a": 0.014, "16b": 0.0}, "9b": {"0a": 0.016, "1a": 0.0, "2a": 0.0, "3a": 0.0, "4a": 0.0, "5a": 0.0, "6a": 0.0, "7a": 0.0, "8a": 0.0, "9b": 0.764, "10a": 0.016, "10b": 0.076, "11b": 0.0, "12a": 0.023, "12b": 0.105, "13a": 0.0, "13b": 0.0, "14a": 0.0, "14b": 0.0, "15a": 0.0, "15b": 0.0, "16a": 0.0, "16b": 0.0}, "10a": {"0a": 0.027, "1a": 0.322, "2a": 0.044, "3a": 0.002, "4a": 0.009, "5a": 0.0, "6a": 0.0, "7a": 0.0, "8a": 0.0, "9b": 0.0, "10a": 0.145, "10b": 0.451, "11b": 0.0, "12a": 0.0, "12b": 0.0, "13a": 0.0, "13b": 0.0, "14a": 0.0, "14b": 0.0, "15a": 0.0, "15b": 0.0, "16a": 0.0, "16b": 0.0}, "10b": {"0a": 0.005, "1a": 0.088, "2a": 0.007, "3a": 0.0, "4a": 0.001, "5a": 0.0, "6a": 0.0, "7a": 0.0, "8a": 0.0, "9b": 0.0, "10a": 0.08, "10b": 0.819, "11b": 0.0, "12a": 0.0, "12b": 0.0, "13a": 0.0, "13b": 0.0, "14a": 0.0, "14b": 0.0, "15a": 0.0, "15b": 0.0, "16a": 0.0, "16b": 0.0}, "11b": {"0a": 0.0, "1a": 0.0, "2a": 0.016, "3a": 0.0, "4a": 0.0, "5a": 0.0, "6a": 0.0, "7a": 0.0, "8a": 0.0, "9b": 0.0, "10a": 0.01, "10b": 0.066, "11b": 0.767, "12a": 0.0, "12b": 0.0, "13a": 0.037, "13b": 0.104, "14a": 0.0, "14b": 0.0, "15a": 0.0, "15b": 0.0, "16a": 0.0, "16b": 0.0}, "12a": {"0a": 0.006, "1a": 0.0, "2a": 0.0, "3a": 0.039, "4a": 0.0, "5a": 0.0, "6a": 0.017, "7a": 0.0, "8a": 0.0, "9b": 0.0, "10a": 0.0, "10b": 0.0, "11b": 0.0, "12a": 0.885, "12b": 0.051, "13a": 0.0, "13b": 0.0, "14a": 0.002, "14b": 0.0, "15a": 0.0, "15b": 0.0, "16a": 0.0, "16b": 0.0}, "12b": {"0a": 0, "1a": 0, "2a": 0, "3a": 0, "4a": 0, "5a": 0, "6a": 0, "7a": 0, "8a": 0, "9b": 0, "10a": 0, "10b": 0, "11b": 0, "12a": 0, "12b": 1, "13a": 0, "13b": 0, "14a": 0, "14b": 0, "15a": 0, "15b": 0, "16a": 0, "16b": 0}, "13a": {"0a": 0.0, "1a": 0.0, "2a": 0.002, "3a": 0.0, "4a": 0.0, "5a": 0.02, "6a": 0.0, "7a": 0.0, "8a": 0.011, "9b": 0.0, "10a": 0.0, "10b": 0.0, "11b": 0.0, "12a": 0.0, "12b": 0.0, "13a": 0.93, "13b": 0.032, "14a": 0.0, "14b": 0.0, "15a": 0.0, "15b": 0.0, "16a": 0.005, "16b": 0.0}, "13b": {"0a": 0, "1a": 0, "2a": 0, "3a": 0, "4a": 0, "5a": 0, "6a": 0, "7a": 0, "8a": 0, "9b": 0, "10a": 0, "10b": 0, "11b": 0, "12a": 0, "12b": 0, "13a": 0, "13b": 1, "14a": 0, "14b": 0, "15a": 0, "15b": 0, "16a": 0, "16b": 0}, "14a": {"0a": 0.0, "1a": 0.0, "2a": 0.0, "3a": 0.0, "4a": 0.0, "5a": 0.0, "6a": 0.007, "7a": 0.0, "8a": 0.0, "9b": 0.0, "10a": 0.0, "10b": 0.0, "11b": 0.0, "12a": 0.116, "12b": 0.011, "13a": 0.0, "13b": 0.0, "14a": 0.668, "14b": 0.147, "15a": 0.05, "15b": 0.001, "16a": 0.0, "16b": 0.0}, "14b": {"0a": 0, "1a": 0, "2a": 0, "3a": 0, "4a": 0, "5a": 0, "6a": 0, "7a": 0, "8a": 0, "9b": 0, "10a": 0, "10b": 0, "11b": 0, "12a": 0, "12b": 0, "13a": 0, "13b": 0, "14a": 0, "14b": 1, "15a": 0, "15b": 0, "16a": 0, "16b": 0}, "15a": {"0a": 0.0, "1a": 0.0, "2a": 0.0, "3a": 0.0, "4a": 0.0, "5a": 0.0, "6a": 0.012, "7a": 0.105, "8a": 0.006, "9b": 0.0, "10a": 0.0, "10b": 0.0, "11b": 0.0, "12a": 0.0, "12b": 0.0, "13a": 0.0, "13b": 0.0, "14a": 0.0, "14b": 0.0, "15a": 0.77, "15b": 0.107, "16a": 0.0, "16b": 0.0}, "15b": {"0a": 0.0, "1a": 0.0, "2a": 0.0, "3a": 0.0, "4a": 0.001, "5a": 0.0, "6a": 0.0, "7a": 0.008, "8a": 0.001, "9b": 0.0, "10a": 0.0, "10b": 0.0, "11b": 0.0, "12a": 0.0, "12b": 0.0, "13a": 0.0, "13b": 0.0, "14a": 0.0, "14b": 0.0, "15a": 0.593, "15b": 0.397, "16a": 0.0, "16b": 0.0}, "16a": {"0a": 0.0, "1a": 0.0, "2a": 0.0, "3a": 0.0, "4a": 0.0, "5a": 0.0, "6a": 0.0, "7a": 0.0, "8a": 0.008, "9b": 0.0, "10a": 0.0, "10b": 0.0, "11b": 0.0, "12a": 0.0, "12b": 0.0, "13a": 0.129, "13b": 0.004, "14a": 0.0, "14b": 0.0, "15a": 0.044, "15b": 0.006, "16a": 0.619, "16b": 0.19}, "16b": {"0a": 0, "1a": 0, "2a": 0, "3a": 0, "4a": 0, "5a": 0, "6a": 0, "7a": 0, "8a": 0, "9b": 0, "10a": 0, "10b": 0, "11b": 0, "12a": 0, "12b": 0, "13a": 0, "13b": 0, "14a": 0, "14b": 0, "15a": 0, "15b": 0, "16a": 0, "16b": 1}}, "SI": {"0a": {"0a": 0.571, "1a": 0.096, "2a": 0.0, "3a": 0.066, "4a": 0.013, "5a": 0.0, "6a": 0.0, "7a": 0.0, "8a": 0.0, "9b": 0.019, "10a": 0.045, "10b": 0.054, "11b": 0.0, "12a": 0.136, "12b": 0.0, "13a": 0.0, "13b": 0.0, "14a": 0.0, "14b": 0.0, "15a": 0.0, "15b": 0.0, "16b": 0.0}, "1a": {"0a": 0.121, "1a": 0.596, "2a": 0.102, "3a": 0.008, "4a": 0.077, "5a": 0.009, "6a": 0.0, "7a": 0.0, "8a": 0.0, "9b": 0.0, "10a": 0.05, "10b": 0.037, "11b": 0.0, "12a": 0.0, "12b": 0.0, "13a": 0.0, "13b": 0.0, "14a": 0.0, "14b": 0.0, "15a": 0.0, "15b": 0.0, "16b": 0.0}, "2a": {"0a": 0.0, "1a": 0.111, "2a": 0.6, "3a": 0.0, "4a": 0.015, "5a": 0.062, "6a": 0.0, "7a": 0.0, "8a": 0.0, "9b": 0.0, "10a": 0.057, "10b": 0.033, "11b": 0.014, "12a": 0.0, "12b": 0.0, "13a": 0.106, "13b": 0.002, "14a": 0.0, "14b": 0.0, "15a": 0.0, "15b": 0.0, "16b": 0.0}, "3a": {"0a": 0.071, "1a": 0.01, "2a": 0.0, "3a": 0.579, "4a": 0.105, "5a": 0.001, "6a": 0.065, "7a": 0.012, "8a": 0.0, "9b": 0.0, "10a": 0.0, "10b": 0.0, "11b": 0.0, "12a": 0.157, "12b": 0.0, "13a": 0.0, "13b": 0.0, "14a": 0.0, "14b": 0.0, "15a": 0.0, "15b": 0.0, "16b": 0.0}, "4a": {"0a": 0.018, "1a": 0.065, "2a": 0.01, "3a": 0.097, "4a": 0.613, "5a": 0.104, "6a": 0.01, "7a": 0.073, "8a": 0.01, "9b": 0.0, "10a": 0.0, "10b": 0.0, "11b": 0.0, "12a": 0.0, "12b": 0.0, "13a": 0.0, "13b": 0.0, "14a": 0.0, "14b": 0.0, "15a": 0.0, "15b": 0.0, "16b": 0.0}, "5a": {"0a": 0.0, "1a": 0.018, "2a": 0.079, "3a": 0.001, "4a": 0.09, "5a": 0.602, "6a": 0.0, "7a": 0.021, "8a": 0.081, "9b": 0.0, "10a": 0.0, "10b": 0.0, "11b": 0.0, "12a": 0.0, "12b": 0.0, "13a": 0.108, "13b": 0.0, "14a": 0.0, "14b": 0.0, "15a": 0.0, "15b": 0.0, "16b": 0.0}, "6a": {"0a": 0.0, "1a": 0.0, "2a": 0.0, "3a": 0.08, "4a": 0.011, "5a": 0.0, "6a": 0.607, "7a": 0.103, "8a": 0.0, "9b": 0.0, "10a": 0.0, "10b": 0.0, "11b": 0.0, "12a": 0.097, "12b": 0.0, "13a": 0.0, "13b": 0.0, "14a": 0.015, "14b": 0.0, "15a": 0.087, "15b": 0.0, "16b": 0.0}, "7a": {"0a": 0.0, "1a": 0.0, "2a": 0.0, "3a": 0.012, "4a": 0.076, "5a": 0.011, "6a": 0.1, "7a": 0.596, "8a": 0.106, "9b": 0.0, "10a": 0.0, "10b": 0.0, "11b": 0.0, "12a": 0.0, "12b": 0.0, "13a": 0.001, "13b": 0.0, "14a": 0.0, "14b": 0.0, "15a": 0.098, "15b": 0.0, "16b": 0.0}, "8a": {"0a": 0.0, "1a": 0.0, "2a": 0.0, "3a": 0.0, "4a": 0.013, "5a": 0.081, "6a": 0.0, "7a": 0.1, "8a": 0.606, "9b": 0.0, "10a": 0.0, "10b": 0.0, "11b": 0.0, "12a": 0.0, "12b": 0.0, "13a": 0.091, "13b": 0.006, "14a": 0.0, "14b": 0.0, "15a": 0.094, "15b": 0.0, "16b": 0.009}, "9b": {"0a": 0.01, "1a": 0.0, "2a": 0.0, "3a": 0.0, "4a": 0.0, "5a": 0.0, "6a": 0.0, "7a": 0.0, "8a": 0.0, "9b": 0.808, "10a": 0.021, "10b": 0.083, "11b": 0.0, "12a": 0.078, "12b": 0.0, "13a": 0.0, "13b": 0.0, "14a": 0.0, "14b": 0.0, "15a": 0.0, "15b": 0.0, "16b": 0.0}, "10a": {"0a": 0.058, "1a": 0.294, "2a": 0.053, "3a": 0.0, "4a": 0.0, "5a": 0.0, "6a": 0.0, "7a": 0.0, "8a": 0.0, "9b": 0.0, "10a": 0.178, "10b": 0.416, "11b": 0.001, "12a": 0.0, "12b": 0.0, "13a": 0.0, "13b": 0.0, "14a": 0.0, "14b": 0.0, "15a": 0.0, "15b": 0.0, "16b": 0.0}, "10b": {"0a": 0.004, "1a": 0.057, "2a": 0.013, "3a": 0.0, "4a": 0.0, "5a": 0.0, "6a": 0.0, "7a": 0.0, "8a": 0.0, "9b": 0.0, "10a": 0.071, "10b": 0.855, "11b": 0.0, "12a": 0.0, "12b": 0.0, "13a": 0.0, "13b": 0.0, "14a": 0.0, "14b": 0.0, "15a": 0.0, "15b": 0.0, "16b": 0.0}, "11b": {"0a": 0.0, "1a": 0.0, "2a": 0.008, "3a": 0.0, "4a": 0.0, "5a": 0.0, "6a": 0.0, "7a": 0.0, "8a": 0.0, "9b": 0.0, "10a": 0.018, "10b": 0.108, "11b": 0.774, "12a": 0.0, "12b": 0.0, "13a": 0.061, "13b": 0.031, "14a": 0.0, "14b": 0.0, "15a": 0.0, "15b": 0.0, "16b": 0.0}, "12a": {"0a": 0.002, "1a": 0.0, "2a": 0.0, "3a": 0.047, "4a": 0.0, "5a": 0.0, "6a": 0.007, "7a": 0.0, "8a": 0.0, "9b": 0.0, "10a": 0.0, "10b": 0.0, "11b": 0.0, "12a": 0.889, "12b": 0.055, "13a": 0.0, "13b": 0.0, "14a": 0.0, "14b": 0.0, "15a": 0.0, "15b": 0.0, "16b": 0.0}, "12b": {"0a": 0.0, "1a": 0.0, "2a": 0.0, "3a": 0.004, "4a": 0.0, "5a": 0.0, "6a": 0.0, "7a": 0.0, "8a": 0.0, "9b": 0.0, "10a": 0.0, "10b": 0.0, "11b": 0.0, "12a": 0.65, "12b": 0.345, "13a": 0.0, "13b": 0.0, "14a": 0.0, "14b": 0.001, "15a": 0.0, "15b": 0.0, "16b": 0.0}, "13a": {"0a": 0.0, "1a": 0.0, "2a": 0.024, "3a": 0.0, "4a": 0.0, "5a": 0.165, "6a": 0.0, "7a": 0.001, "8a": 0.011, "9b": 0.0, "10a": 0.0, "10b": 0.0, "11b": 0.0, "12a": 0.0, "12b": 0.0, "13a": 0.546, "13b": 0.253, "14a": 0.0, "14b": 0.0, "15a": 0.0, "15b": 0.0, "16b": 0.0}, "13b": {"0a": 0.0, "1a": 0.0, "2a": 0.004, "3a": 0.0, "4a": 0.0, "5a": 0.015, "6a": 0.0, "7a": 0.0, "8a": 0.006, "9b": 0.0, "10a": 0.0, "10b": 0.0, "11b": 0.0, "12a": 0.0, "12b": 0.0, "13a": 0.317, "13b": 0.658, "14a": 0.0, "14b": 0.0, "15a": 0.0, "15b": 0.0, "16b": 0.0}, "14a": {"0a": 0.0, "1a": 0.0, "2a": 0.0, "3a": 0.0, "4a": 0.0, "5a": 0.0, "6a": 0.013, "7a": 0.0, "8a": 0.0, "9b": 0.0, "10a": 0.0, "10b": 0.0, "11b": 0.0, "12a": 0.13, "12b": 0.006, "13a": 0.0, "13b": 0.0, "14a": 0.607, "14b": 0.177, "15a": 0.059, "15b": 0.008, "16b": 0.0}, "14b": {"0a": 0, "1a": 0, "2a": 0, "3a": 0, "4a": 0, "5a": 0, "6a": 0, "7a": 0, "8a": 0, "9b": 0, "10a": 0, "10b": 0, "11b": 0, "12a": 0, "12b": 0, "13a": 0, "13b": 0, "14a": 0, "14b": 1, "15a": 0, "15b": 0, "16b": 0}, "15a": {"0a": 0.0, "1a": 0.0, "2a": 0.0, "3a": 0.0, "4a": 0.0, "5a": 0.0, "6a": 0.013, "7a": 0.116, "8a": 0.014, "9b": 0.0, "10a": 0.0, "10b": 0.0, "11b": 0.0, "12a": 0.0, "12b": 0.0, "13a": 0.0, "13b": 0.0, "14a": 0.0, "14b": 0.0, "15a": 0.728, "15b": 0.129, "16b": 0.0}, "15b": {"0a": 0.0, "1a": 0.0, "2a": 0.0, "3a": 0.0, "4a": 0.0, "5a": 0.0, "6a": 0.002, "7a": 0.012, "8a": 0.002, "9b": 0.0, "10a": 0.0, "10b": 0.0, "11b": 0.0, "12a": 0.0, "12b": 0.0, "13a": 0.0, "13b": 0.0, "14a": 0.0, "14b": 0.001, "15a": 0.426, "15b": 0.557, "16b": 0.0}, "16b": {"0a": 0.0, "1a": 0.0, "2a": 0.0, "3a": 0.0, "4a": 0.0, "5a": 0.0, "6a": 0.0, "7a": 0.0, "8a": 0.007, "9b": 0.0, "10a": 0.0, "10b": 0.0, "11b": 0.0, "12a": 0.0, "12b": 0.0, "13a": 0.056, "13b": 0.034, "14a": 0.0, "14b": 0.0, "15a": 0.084, "15b": 0.026, "16b": 0.793}}}